Workbook
Name aporte: Planilha1!$E$22

Sheet Planilha1
B16: Configurações
B17: Salario | E17: 5000
B18: Rendimento de carteira | E18: 0.006
B19: sugestação de valor | E19: =E17*30% -> 1500
B21: Investimento
B22: Quanto investir por mês? | E22: 500
B23: por quanto anos? | E23: 5
B24: Taxa de rendimento por mês? | E24: 0.01079
B25: Patrimonio acumulado? | E25: =FV(E24,E23*12,E22*-1) -> 41888.457
B26: Dividendo mensais? | E26: 5
B28: Cenário | H28: Dividendos
A29: 2 | B29: Quanto em 2 anos? | E29: =FV($E$24,A29*12,$E$22*-1) -> 13613.814 | H29: =E29*$E$18 -> 81.682882
A30: 5 | B30: Quanto em 5 anos? | E30: =FV($E$24,A30*12,$E$22*-1) -> 41888.457 | H30: =E30*$E$18 -> 251.33074
A31: 10 | B31: Quanto em 10 anos? | E31: =FV($E$24,A31*12,$E$22*-1) -> 121642.11 | H31: =E31*$E$18 -> 729.85264
A32: 20 | B32: Quanto em 20 anos? | E32: =FV($E$24,A32*12,$E$22*-1) -> 562599.2 | H32: =E32*$E$18 -> 3375.5952
A33: 30 | B33: Quanto em 30 anos? | E33: =FV($E$24,A33*12,$E$22*-1) -> 2161084.8 | H33: =E33*$E$18 -> 12966.509
B35: Perfil: | H35: Moderado
B37: Valor mensal de investimento | H37: =aporte -> 500
B39: Tipo de FII | H39: % sugerido | J39: Valores
B40: Papel | H40: =VLOOKUP($H$35&"-"&B40,Planilha2!A1:D19,4,FALSE) -> 0.32 | J40: =$H$37*H40 -> 160
B41: Tijolo | H41: =VLOOKUP($H$35&"-"&B41,Planilha2!A2:D20,4,FALSE) -> 0.35 | J41: =$H$37*H41 -> 175
B42: Hibridos | H42: =VLOOKUP($H$35&"-"&B42,Planilha2!A3:D21,4,FALSE) -> 0.05 | J42: =$H$37*H42 -> 25
B43: Fof's | H43: =VLOOKUP($H$35&"-"&B43,Planilha2!A4:D22,4,FALSE) -> 0.08 | J43: =$H$37*H43 -> 40
B44: Desenvolviemtno | H44: =VLOOKUP($H$35&"-"&B44,Planilha2!A5:D23,4,FALSE) -> 0.1 | J44: =$H$37*H44 -> 50
B45: Hotelaria | H45: =VLOOKUP($H$35&"-"&B45,Planilha2!A6:D24,4,FALSE) -> 0.1 | J45: =$H$37*H45 -> 50
B47: Valor final: | J47: =SUM(J40:J46) -> 500

Sheet Planilha2
A1: Chave Composta | B1: Perfil | C1: Tipo de FII | D1: Poercentagem
A2: =B2&"-"&C2 -> Conservador-Papel | B2: Conservador | C2: Papel | D2: 0.3
A3: =B3&"-"&C3 -> Conservador-Tijolo | B3: Conservador | C3: Tijolo | D3: 0.5 | G3: Conservador-Tijolo | H3: =VLOOKUP(G3,A1:D19,4,FALSE) -> 0.5
A4: =B4&"-"&C4 -> Conservador-Hibridos | B4: Conservador | C4: Hibridos | D4: 0.1
A5: =B5&"-"&C5 -> Conservador-Fof's | B5: Conservador | C5: Fof's | D5: 0.1
A6: =B6&"-"&C6 -> Conservador-Desenvolviemtno | B6: Conservador | C6: Desenvolviemtno | D6: 0
A7: =B7&"-"&C7 -> Conservador-Hotelaria | B7: Conservador | C7: Hotelaria | D7: 0
A8: =B8&"-"&C8 -> Moderado-Papel | B8: Moderado | C8: Papel | D8: 0.32
A9: =B9&"-"&C9 -> Moderado-Tijolo | B9: Moderado | C9: Tijolo | D9: 0.35
A10: =B10&"-"&C10 -> Moderado-Hibridos | B10: Moderado | C10: Hibridos | D10: 0.05
A11: =B11&"-"&C11 -> Moderado-Fof's | B11: Moderado | C11: Fof's | D11: 0.08
A12: =B12&"-"&C12 -> Moderado-Desenvolviemtno | B12: Moderado | C12: Desenvolviemtno | D12: 0.1
A13: =B13&"-"&C13 -> Moderado-Hotelaria | B13: Moderado | C13: Hotelaria | D13: 0.1
A14: =B14&"-"&C14 -> Agressivo-Papel | B14: Agressivo | C14: Papel | D14: 0.5
A15: =B15&"-"&C15 -> Agressivo-Tijolo | B15: Agressivo | C15: Tijolo | D15: 0.1
... A19: =B19&"-"&C19 -> Agressivo-Hotelaria | B19: Agressivo | C19: Hotelaria | D19: 0.1
